ragout/__init__.py
ragout/cmaf2synteny.so
ragout/coverlap.so
ragout/main.py
ragout/assembly_graph/__init__.py
ragout/assembly_graph/assembly_refine.py
ragout/breakpoint_graph/__init__.py
ragout/breakpoint_graph/breakpoint_graph.py
ragout/breakpoint_graph/permutation.py
ragout/breakpoint_graph/phylogeny.py
ragout/maf2synteny/__init__.py
ragout/maf2synteny/maf2synteny.py
ragout/overlap/__init__.py
ragout/overlap/overlap.py
ragout/parsers/__init__.py
ragout/parsers/config_parser.py
ragout/scaffolder/__init__.py
ragout/scaffolder/merge_iters.py
ragout/scaffolder/scaffolder.py
ragout/shared/__init__.py
ragout/shared/config.py
ragout/shared/datatypes.py
ragout/shared/debug.py
ragout/shared/utils.py
ragout/synteny_backend/__init__.py
ragout/synteny_backend/cactus.py
ragout/synteny_backend/sibelia.py
ragout/synteny_backend/synteny_backend.py
ragout-0.2b.data/data/share/ragout/docs/INSTALL.md
ragout-0.2b.data/data/share/ragout/docs/USAGE.md
ragout-0.2b.dist-info/DESCRIPTION.rst
ragout-0.2b.dist-info/entry_points.txt
ragout-0.2b.dist-info/METADATA
ragout-0.2b.dist-info/metadata.json
ragout-0.2b.dist-info/RECORD
ragout-0.2b.dist-info/top_level.txt
ragout-0.2b.dist-info/WHEEL
