Metadata-Version: 2.0
Name: ragout
Version: 0.2b
Summary: A tool for reference-assisted assembly
Home-page: http://github.com/fenderglass/Ragout
Author: Mikhail Kolmogorov
Author-email: fenderglass@gmail.com
License: GPLv2
Keywords: bioinformatics
Platform: UNKNOWN
Classifier: Development Status :: 4 - Beta
Classifier: Intended Audience :: Science/Research
Classifier: License :: OSI Approved :: GNU General Public License v2 (GPLv2)
Classifier: Operating System :: POSIX
Classifier: Topic :: Scientific/Engineering :: Bio-Informatics
Classifier: Topic :: Utilities
Classifier: Programming Language :: Python
Classifier: Programming Language :: C++
Requires-Dist: biopython
Requires-Dist: networkx (>=1.8)
